README.txt
setup.py
src/rsl/__init__.py
src/rsl.xmlrpc.egg-info/PKG-INFO
src/rsl.xmlrpc.egg-info/SOURCES.txt
src/rsl.xmlrpc.egg-info/dependency_links.txt
src/rsl.xmlrpc.egg-info/entry_points.txt
src/rsl.xmlrpc.egg-info/namespace_packages.txt
src/rsl.xmlrpc.egg-info/requires.txt
src/rsl.xmlrpc.egg-info/top_level.txt
src/rsl/xmlrpc/__init__.py
src/rsl/xmlrpc/factories.py
src/rsl/xmlrpc/proxy.py
src/rsl/xmlrpc/serializer.py
src/rsl/xmlrpc/xmlrpcdescr.py
